importnow/__init__.py
importnow/importnow.py
importnow-0.1.1.dist-info/WHEEL
importnow-0.1.1.dist-info/METADATA
importnow-0.1.1.dist-info/RECORD
