Metadata-Version: 2.1
Name: importnow
Version: 0.1.1
Summary: import for chads https://github.com/msaroufim/importnow
Author: Mark Saroufim
Author-email: marksaroufim@fb.com
Requires-Python: >=3.8,<4.0
Classifier: Programming Language :: Python :: 3
Classifier: Programming Language :: Python :: 3.10
Classifier: Programming Language :: Python :: 3.8
Classifier: Programming Language :: Python :: 3.9
